loguru_kit/__init__.py
loguru_kit/_config.py
loguru_kit/_context.py
loguru_kit/_core.py
loguru_kit/_isolation.py
loguru_kit/py.typed
loguru_kit/integrations/__init__.py
loguru_kit/integrations/fastapi.py
loguru_kit/integrations/otel.py
loguru_kit/integrations/stdlib.py
loguru_kit-0.7.0.dist-info/licenses/LICENSE
loguru_kit-0.7.0.dist-info/METADATA
loguru_kit-0.7.0.dist-info/WHEEL
loguru_kit-0.7.0.dist-info/top_level.txt
loguru_kit-0.7.0.dist-info/RECORD
