Metadata-Version: 2.4
Name: loguru-kit
Version: 0.7.0
Summary: Dead simple loguru setup
Author-email: JunSeok Kim <infend@gmail.com>
License: MIT
Project-URL: Homepage, https://github.com/bestend/loguru-kit
Project-URL: Documentation, https://github.com/bestend/loguru-kit#readme
Project-URL: Repository, https://github.com/bestend/loguru-kit.git
Project-URL: Issues, https://github.com/bestend/loguru-kit/issues
Keywords: loguru,logging,fastapi,opentelemetry
Classifier: Development Status :: 3 - Alpha
Classifier: Intended Audience :: Developers
Classifier: License :: OSI Approved :: MIT License
Classifier: Programming Language :: Python :: 3
Classifier: Programming Language :: Python :: 3.12
Classifier: Programming Language :: Python :: 3.13
Classifier: Programming Language :: Python :: 3.14
Classifier: Topic :: System :: Logging
Requires-Python: >=3.12
License-File: LICENSE
Requires-Dist: loguru>=0.7.0
Provides-Extra: fastapi
Requires-Dist: starlette>=0.27.0; extra == "fastapi"
Provides-Extra: otel
Requires-Dist: opentelemetry-api>=1.20.0; extra == "otel"
Provides-Extra: all
Requires-Dist: starlette>=0.27.0; extra == "all"
Requires-Dist: opentelemetry-api>=1.20.0; extra == "all"
Dynamic: license-file
